setup.cfg
setup.py
localise/__init__.py
localise/basicconfig.py
localise/commands.py
localise/localise.py
loco_cli.egg-info/PKG-INFO
loco_cli.egg-info/SOURCES.txt
loco_cli.egg-info/dependency_links.txt
loco_cli.egg-info/entry_points.txt
loco_cli.egg-info/requires.txt
loco_cli.egg-info/top_level.txt