Metadata-Version: 1.1
Name: loco-cli
Version: 0.2.1
Summary: Command line utiltiy for Localise.biz.
Home-page: https://pypi.python.org/pypi/loco-cli/
Author: Martin Malek
Author-email: martin.malek@pagewiser.com
License: MIT
Download-URL: https://github.com/marten-cz/loco-cli
Platform: any
Classifier: Development Status :: 3 - Alpha
Classifier: Environment :: Console
Classifier: Intended Audience :: Developers
Classifier: License :: OSI Approved :: MIT License
Classifier: Operating System :: OS Independent
Classifier: Topic :: Software Development :: Localization
Classifier: Programming Language :: Python :: 2.7
Classifier: Programming Language :: Python :: 3
